Metadata-Version: 2.1
Name: xnat-nott
Version: 0.1.0.post4
Summary: Helper functions for XNAT applications/containers
Author: Martin Craig
Author-email: martin.craig@nottingham.ac.uk
License: Apache-2.0
Classifier: Intended Audience :: Science/Research
Classifier: Programming Language :: Python :: 3
Classifier: License :: OSI Approved :: Apache Software License
License-File: LICENSE
